jupyterlab_search_replace/__init__.py
jupyterlab_search_replace/_version.py
jupyterlab_search_replace/handlers.py
jupyterlab_search_replace/log.py
jupyterlab_search_replace/search_engine.py
jupyterlab_search_replace/tests/__init__.py
jupyterlab_search_replace/tests/conftest.py
jupyterlab_search_replace/tests/schema.json
jupyterlab_search_replace/tests/test_handlers.py
jupyterlab_search_replace/tests/test_search_engine.py
jupyterlab_search_replace-1.1.2.data/data/etc/jupyter/jupyter_server_config.d/jupyterlab_search_replace.json
jupyterlab_search_replace-1.1.2.data/data/share/jupyter/labextensions/jupyterlab-search-replace/package.json
jupyterlab_search_replace-1.1.2.data/data/share/jupyter/labextensions/jupyterlab-search-replace/schemas/jupyterlab-search-replace/package.json.orig
jupyterlab_search_replace-1.1.2.data/data/share/jupyter/labextensions/jupyterlab-search-replace/schemas/jupyterlab-search-replace/plugin.json
jupyterlab_search_replace-1.1.2.data/data/share/jupyter/labextensions/jupyterlab-search-replace/static/28.aeaa97c8a39b21427254.js
jupyterlab_search_replace-1.1.2.data/data/share/jupyter/labextensions/jupyterlab-search-replace/static/377.f0f2703120c65feabe65.js
jupyterlab_search_replace-1.1.2.data/data/share/jupyter/labextensions/jupyterlab-search-replace/static/441.fd3dc648d2d41d6ac73a.js
jupyterlab_search_replace-1.1.2.data/data/share/jupyter/labextensions/jupyterlab-search-replace/static/50.b526e902f8ed2be0539e.js
jupyterlab_search_replace-1.1.2.data/data/share/jupyter/labextensions/jupyterlab-search-replace/static/590.d38749ba0c67a8150efb.js
jupyterlab_search_replace-1.1.2.data/data/share/jupyter/labextensions/jupyterlab-search-replace/static/728.30667c569a38af1e18a5.js
jupyterlab_search_replace-1.1.2.data/data/share/jupyter/labextensions/jupyterlab-search-replace/static/794.be0593b6a442fd5d757c.js
jupyterlab_search_replace-1.1.2.data/data/share/jupyter/labextensions/jupyterlab-search-replace/static/822.75e1b8962fda3bb978dd.js
jupyterlab_search_replace-1.1.2.dist-info/METADATA
jupyterlab_search_replace-1.1.2.dist-info/WHEEL
jupyterlab_search_replace-1.1.2.dist-info/licenses/LICENSE
jupyterlab_search_replace-1.1.2.dist-info/RECORD
